timeseries-shaper/__init__.py
timeseries-shaper/base.py
timeseries-shaper/events/__init__.py
timeseries-shaper/events/tolerance_deviation.py
timeseries-shaper/filter/__init__.py
timeseries-shaper/filter/boolean_filter.py
timeseries-shaper/filter/custom_filter.py
timeseries-shaper/filter/datetime_filters.py
timeseries-shaper/filter/numeric_filters.py
timeseries-shaper/filter/string_filters.py
timeseries-shaper/stats/__init__.py
timeseries_shaper/__init__.py
timeseries_shaper/base.py
timeseries_shaper/calculator/__init__.py
timeseries_shaper/calculator/numeric_calc.py
timeseries_shaper/cycles/__init__.py
timeseries_shaper/cycles/cycle_processor.py
timeseries_shaper/cycles/cycles.py
timeseries_shaper/cycles/cycles_extractor.py
timeseries_shaper/events/__init__.py
timeseries_shaper/events/outlier_detection.py
timeseries_shaper/events/statistical_process_control.py
timeseries_shaper/events/tolerance_deviation.py
timeseries_shaper/events/value_mapping.py
timeseries_shaper/filter/__init__.py
timeseries_shaper/filter/boolean_filter.py
timeseries_shaper/filter/custom_filter.py
timeseries_shaper/filter/datetime_filter.py
timeseries_shaper/filter/datetime_filters.py
timeseries_shaper/filter/numeric_filter.py
timeseries_shaper/filter/numeric_filters.py
timeseries_shaper/filter/string_filter.py
timeseries_shaper/filter/string_filters.py
timeseries_shaper/functions/__init__.py
timeseries_shaper/functions/lambda_func.py
timeseries_shaper/loader/__init__.py
timeseries_shaper/loader/combine/__init__.py
timeseries_shaper/loader/combine/combine_with_metadata.py
timeseries_shaper/loader/combine/integrator.py
timeseries_shaper/loader/metadata/__init__.py
timeseries_shaper/loader/metadata/metadata_api_loader.py
timeseries_shaper/loader/metadata/metadata_db_loader.py
timeseries_shaper/loader/metadata/metadata_json_loader.py
timeseries_shaper/loader/timeseries/__init__.py
timeseries_shaper/loader/timeseries/parquet_loader.py
timeseries_shaper/loader/timeseries/s3proxy_parquet_loader.py
ts_shape-0.0.0.30.dist-info/LICENSE.txt
ts_shape-0.0.0.30.dist-info/METADATA
ts_shape-0.0.0.30.dist-info/WHEEL
ts_shape-0.0.0.30.dist-info/top_level.txt
ts_shape-0.0.0.30.dist-info/RECORD
