Metadata-Version: 2.1
Name: ts-shape
Version: 0.0.0.30
Summary: ts-shape filters, transforms and engineers your timeseries dataframe
Home-page: https://jakobgabriel.github.io/ts-shape/
Author: Jakob Gabriel
Author-email: jakob.gabriel5@googlemail.com
Project-URL: Bug Tracker, https://github.com/jakobgabriel/ts-shape
Classifier: Programming Language :: Python :: 3
Classifier: License :: OSI Approved :: MIT License
Classifier: Operating System :: OS Independent
Requires-Python: >=3.10
License-File: LICENSE.txt
